better_elided_pagination/__init__.py
better_elided_pagination/paginators.py
django_better_elided_pagination-1.2.2.dist-info/METADATA
django_better_elided_pagination-1.2.2.dist-info/WHEEL
django_better_elided_pagination-1.2.2.dist-info/top_level.txt
django_better_elided_pagination-1.2.2.dist-info/RECORD
